LICENCE
MANIFEST.in
README.mkd
requirements.txt
setup.py
pyrosalind/__init__.py
pyrosalind/__main__.py
pyrosalind/info.py
pyrosalind/parser.py
pyrosalind/user.py
pyrosalind.egg-info/PKG-INFO
pyrosalind.egg-info/SOURCES.txt
pyrosalind.egg-info/dependency_links.txt
pyrosalind.egg-info/requires.txt
pyrosalind.egg-info/top_level.txt