Metadata-Version: 1.1
Name: pyrosalind
Version: 0.1.1
Summary: Parse information found on the http://rosalind.info website
Home-page: https://github.com/Aluriak/pyrosalind
Author: lucas bourneuf
Author-email: lucas.bourneuf@openmailbox.org
License: UNKNOWN
Keywords: graph
Platform: UNKNOWN
Classifier: Development Status :: 2 - Pre-Alpha
Classifier: Intended Audience :: Science/Research
Classifier: License :: OSI Approved :: GNU General Public License (GPL)
Classifier: Natural Language :: English
Classifier: Programming Language :: Python :: 3
Classifier: Topic :: Software Development :: Libraries :: Python Modules
